djangocms_revealjs/__init__.py
djangocms_revealjs/cms_plugins.py
djangocms_revealjs/models.py
djangocms_revealjs/migrations/0001_initial.py
djangocms_revealjs/migrations/__init__.py
djangocms_revealjs/south_migrations/0001_initial.py
djangocms_revealjs/south_migrations/0002_auto__add_slidenote__add_slidecode__del_field_slidemodel_markdown.py
djangocms_revealjs/south_migrations/__init__.py
djangocms_revealjs/static/css/reveal.css
djangocms_revealjs/static/css/style.css
djangocms_revealjs/static/css/print/paper.css
djangocms_revealjs/static/css/print/pdf.css
djangocms_revealjs/static/css/theme/beige.css
djangocms_revealjs/static/css/theme/black.css
djangocms_revealjs/static/css/theme/blood.css
djangocms_revealjs/static/css/theme/default.css
djangocms_revealjs/static/css/theme/league.css
djangocms_revealjs/static/css/theme/moon.css
djangocms_revealjs/static/css/theme/night.css
djangocms_revealjs/static/css/theme/serif.css
djangocms_revealjs/static/css/theme/simple.css
djangocms_revealjs/static/css/theme/sky.css
djangocms_revealjs/static/css/theme/solarized.css
djangocms_revealjs/static/css/theme/white.css
djangocms_revealjs/static/img/fragment.png
djangocms_revealjs/static/img/slide_code.png
djangocms_revealjs/static/img/slide_note.png
djangocms_revealjs/static/js/reveal.js
djangocms_revealjs/static/lib/css/zenburn.css
djangocms_revealjs/static/lib/font/league_gothic-webfont.svg
djangocms_revealjs/static/lib/font/league-gothic/league-gothic.css
djangocms_revealjs/static/lib/font/source-sans-pro/source-sans-pro.css
djangocms_revealjs/static/lib/js/classList.js
djangocms_revealjs/static/lib/js/head.min.js
djangocms_revealjs/static/lib/js/html5shiv.js
djangocms_revealjs/static/plugin/highlight/highlight.js
djangocms_revealjs/static/plugin/leap/leap.js
djangocms_revealjs/static/plugin/markdown/example.html
djangocms_revealjs/static/plugin/markdown/markdown.js
djangocms_revealjs/static/plugin/markdown/marked.js
djangocms_revealjs-0.3.dist-info/DESCRIPTION.rst
djangocms_revealjs-0.3.dist-info/METADATA
djangocms_revealjs-0.3.dist-info/RECORD
djangocms_revealjs-0.3.dist-info/WHEEL
djangocms_revealjs-0.3.dist-info/metadata.json
djangocms_revealjs-0.3.dist-info/top_level.txt
