Metadata-Version: 2.0
Name: djangocms-revealjs
Version: 0.3
Summary: django CMS plugin to create reveal.js presentations
Home-page: https://github.com/nephila/djangocms-revealjs
Author: Iacopo Spalletti
Author-email: i.spalletti@nephila.it
License: BSD
Keywords: djangocms-revealjs,django CMS,reveal.js,django
Platform: UNKNOWN
Classifier: Development Status :: 2 - Pre-Alpha
Classifier: Framework :: Django
Classifier: Intended Audience :: Developers
Classifier: License :: OSI Approved :: BSD License
Classifier: Natural Language :: English
Classifier: Programming Language :: Python :: 2
Classifier: Programming Language :: Python :: 2.6
Classifier: Programming Language :: Python :: 2.7
Classifier: Programming Language :: Python :: 3
Classifier: Programming Language :: Python :: 3.3
Requires-Dist: cmsplugin-filer
Requires-Dist: django-cms (>=3.0)
Requires-Dist: django-filer
Requires-Dist: djangocms-text-ckeditor
